matcouply/__init__.py
matcouply/_doc_utils.py
matcouply/_unimodal_regression.py
matcouply/_utils.py
matcouply/conftest.py
matcouply/coupled_matrices.py
matcouply/data.py
matcouply/decomposition.py
matcouply/penalties.py
matcouply/random.py
matcouply/datasets/bike.zip
matcouply/testing/__init__.py
matcouply/testing/admm_penalty.py
matcouply/testing/fixtures.py
matcouply/testing/utils.py
matcouply-0.1.6.dist-info/LICENSE
matcouply-0.1.6.dist-info/METADATA
matcouply-0.1.6.dist-info/WHEEL
matcouply-0.1.6.dist-info/top_level.txt
matcouply-0.1.6.dist-info/RECORD
