Metadata-Version: 2.1
Name: matcouply
Version: 0.1.6
Summary: Regularized coupled matrix factorisation with AO-ADMM
Home-page: https://github.com/marieroald/matcouply
Author: Marie Roald
Author-email: roald.marie@gmail.com
License: MIT
Keywords: matcouply
Classifier: Development Status :: 2 - Pre-Alpha
Classifier: Intended Audience :: Developers
Classifier: License :: OSI Approved :: MIT License
Classifier: Natural Language :: English
Classifier: Programming Language :: Python :: 3.6
Classifier: Programming Language :: Python :: 3.7
Classifier: Programming Language :: Python :: 3.8
Classifier: Programming Language :: Python :: 3.9
Requires-Python: >=3.6
License-File: LICENSE
Requires-Dist: numpy
Requires-Dist: scipy
Requires-Dist: tensorly
Provides-Extra: data
Requires-Dist: pandas ; extra == 'data'
Requires-Dist: tqdm ; extra == 'data'
Requires-Dist: requests ; extra == 'data'
Provides-Extra: devel
Requires-Dist: coverage ; extra == 'devel'
Requires-Dist: pytest ; extra == 'devel'
Requires-Dist: pytest-cov ; extra == 'devel'
Requires-Dist: pytest-randomly ; extra == 'devel'
Requires-Dist: flake8 ; extra == 'devel'
Requires-Dist: darglint ; extra == 'devel'
Requires-Dist: black ; extra == 'devel'
Requires-Dist: isort ; extra == 'devel'
Requires-Dist: sphinx ; extra == 'devel'
Requires-Dist: sphinx-rtd-theme ; extra == 'devel'
Requires-Dist: sphinx-gallery ; extra == 'devel'
Requires-Dist: sphinxcontrib-bibtex ; extra == 'devel'
Requires-Dist: autodocsumm ; extra == 'devel'
Requires-Dist: nbsphinx ; extra == 'devel'
Requires-Dist: ipython ; extra == 'devel'
Requires-Dist: bump2version ; extra == 'devel'
Requires-Dist: wheel ; extra == 'devel'
Requires-Dist: scikit-learn ; extra == 'devel'
Provides-Extra: examples
Requires-Dist: matplotlib ; extra == 'examples'
Requires-Dist: plotly ; extra == 'examples'
Requires-Dist: wordcloud ; extra == 'examples'
Requires-Dist: tlviz ; extra == 'examples'
Provides-Extra: gpl
Requires-Dist: condat-tv ; extra == 'gpl'
Provides-Extra: numba
Requires-Dist: numpy (>=1.22.1) ; extra == 'numba'
Requires-Dist: numba (==0.53.1) ; extra == 'numba'
Provides-Extra: testing
Requires-Dist: pytest ; extra == 'testing'
